dada/__init__.py
dada/config/base.toml
dada/config/categories.toml
dada/config/kinds.backup.toml
dada/config/kinds2.backup.toml
dada/projects.py
dada/scripts/__init__.py
dada/scripts/dada.py
dada-0.2.0.dist-info/entry_points.txt
dada-0.2.0.dist-info/LICENSE
dada-0.2.0.dist-info/WHEEL
dada-0.2.0.dist-info/METADATA
dada-0.2.0.dist-info/RECORD
