Metadata-Version: 2.1
Name: dada
Version: 0.2.0
Summary: Dada – a CLI project manager
Home-page: UNKNOWN
License: MIT
Author: Dominic Looser
Author-email: dominic.looser@gmail.com
Requires-Python: >=3.7,<4.0
Classifier: Development Status :: 2 - Pre-Alpha
Classifier: License :: OSI Approved :: MIT License
Classifier: Programming Language :: Python :: 3
Classifier: Programming Language :: Python :: 3.7
Requires-Dist: click (>=7.0,<8.0)
Requires-Dist: pick (>=0.6.4,<0.7.0)
Requires-Dist: toml (>=0.10.0,<0.11.0)
